<MessageFrame>
    <messageId>31</messageId>
    <value>
        <timeStamp>31024</timeStamp>
        <packetID>000000000000000001</packetID>
        <urlB>null</urlB>
        <dataFrames>
            <TravelerDataFrame>
                <durationTime>22</durationTime>
                <regions>
                    <GeographicalPath>
                        <closedPath>
                            <false></false>
                        </closedPath>
                        <anchor>
                            <elevation>917</elevation>
                            <lat>-108</lat>
                            <long>41</long>
                        </anchor>
                        <name>bob</name>
                        <laneWidth>700</laneWidth>
                        <directionality>
                            <both></both>
                        </directionality>
                        <description>
                            <geometry>
                                <extent>1</extent>
                                <laneWidth>3300</laneWidth>
                                <circle>
                                    <center>
                                        <elevation>917</elevation>
                                        <lat>-108</lat>
                                        <long>41</long>
                                    </center>
                                    <units>7</units>
                                    <radius>15</radius>
                                </circle>
                                <direction>1010101010101010</direction>
                            </geometry>
                        </description>
                        <id>
                            <id>33</id>
                            <region>23</region>
                        </id>
                        <direction>1010101010101010</direction>
                    </GeographicalPath>
                </regions>
                <sspMsgRights1>2</sspMsgRights1>
                <sspMsgRights2>3</sspMsgRights2>
                <startYear>2017</startYear>
                <msgId>
                    <roadSignID>
                        <crc>0000</crc>
                        <viewAngle>1010101010101010</viewAngle>
                        <mutcdCode>
                            <guide></guide>
                        </mutcdCode>
                        <position>
                            <elevation>917</elevation>
                            <lat>-108</lat>
                            <long>41</long>
                        </position>
                    </roadSignID>
                </msgId>
                <priority>0</priority>
                <url>null</url>
                <sspTimRights>0</sspTimRights>
                <sspLocationRights>3</sspLocationRights>
                <frameType>
                    <unknown></unknown>
                </frameType>
                <startTime>-18752</startTime>
                <content>
                    <advisory>
                        <SEQUENCE>
                            <item>
                                <itis>250</itis>
                            </item>
                        </SEQUENCE>
                    </advisory>
                </content>
            </TravelerDataFrame>
        </dataFrames>
        <msgCnt>13</msgCnt>
    </value>
</MessageFrame>

